package/__init__.py
package/client.py
package/server.py
bgm_net-0.1.1.dist-info/METADATA
bgm_net-0.1.1.dist-info/WHEEL
bgm_net-0.1.1.dist-info/top_level.txt
bgm_net-0.1.1.dist-info/RECORD
