Metadata-Version: 2.2
Name: bgm-net
Version: 0.1.1
Summary: Python library that made for Multiplayer games.
Home-page: https://github.com/DanXvoIsMe/BGM
Author: DanXvo
Author-email: data.com0010@gmail.com
Classifier: Programming Language :: Python :: 3
Classifier: Operating System :: OS Independent
Requires-Python: >=3.6
Requires-Dist: requests
Dynamic: author
Dynamic: author-email
Dynamic: classifier
Dynamic: description
Dynamic: description-content-type
Dynamic: home-page
Dynamic: requires-dist
Dynamic: requires-python
Dynamic: summary
